ganvil/__init__.py
ganvil/controller.py
ganvil/go_plugin/__init__.py
ganvil/go_plugin/grpc_controller_pb2.py
ganvil/go_plugin/grpc_controller_pb2.pyi
ganvil/go_plugin/grpc_controller_pb2_grpc.py
ganvil/go_plugin/grpc_stdio_pb2.py
ganvil/go_plugin/grpc_stdio_pb2.pyi
ganvil/go_plugin/grpc_stdio_pb2_grpc.py
ganvil/protocol/__init__.py
ganvil/protocol/v1/__init__.py
ganvil/protocol/v1/ganvil_pb2.py
ganvil/protocol/v1/ganvil_pb2.pyi
ganvil/protocol/v1/ganvil_pb2_grpc.py
ganvil/sdk.py
ganvil/stdio.py
ganvil-1.0.2.dist-info/LICENSE
ganvil-1.0.2.dist-info/METADATA
ganvil-1.0.2.dist-info/WHEEL
ganvil-1.0.2.dist-info/RECORD
